dbcls/__init__.py
dbcls/autocomplete.py
dbcls/dbcls.py
dbcls/sql_tokenizer.py
dbcls/utils.py
dbcls/vd_db_browser.py
dbcls/clients/__init__.py
dbcls/clients/base.py
dbcls/clients/clickhouse.py
dbcls/clients/mysql.py
dbcls/clients/postgres.py
dbcls/clients/sqlite3.py
dbcls-1.1.23.dist-info/licenses/LICENSE
dbcls-1.1.23.dist-info/METADATA
dbcls-1.1.23.dist-info/WHEEL
dbcls-1.1.23.dist-info/entry_points.txt
dbcls-1.1.23.dist-info/top_level.txt
dbcls-1.1.23.dist-info/RECORD
