Metadata-Version: 2.4
Name: dbcls
Version: 1.1.23
Summary: dbcls is a versatile client that supports various databases
Home-page: https://github.com/Sets88/dbcls
Author: Maksim Nikitenko
Author-email: iam@sets88.com
License: BSD
Platform: any
Requires-Python: >=3.9
License-File: LICENSE
Requires-Dist: kaaedit==0.54.1
Requires-Dist: visidata==3.2
Requires-Dist: clickhouse-connect==0.8.18
Requires-Dist: ciso8601==2.3.0
Requires-Dist: aiomysql==0.2.0
Requires-Dist: aiopg==1.4.0
Requires-Dist: cryptography
Dynamic: author
Dynamic: author-email
Dynamic: description
Dynamic: description-content-type
Dynamic: home-page
Dynamic: license
Dynamic: license-file
Dynamic: platform
Dynamic: requires-dist
Dynamic: requires-python
Dynamic: summary
